azimuthpy/__init__.py
azimuthpy/python_wrapper.py
azimuthpy-0.1.1.dist-info/LICENSE
azimuthpy-0.1.1.dist-info/METADATA
azimuthpy-0.1.1.dist-info/WHEEL
azimuthpy-0.1.1.dist-info/top_level.txt
azimuthpy-0.1.1.dist-info/RECORD
