Metadata-Version: 2.1
Name: azimuthpy
Version: 0.1.1
Summary: Python wrapper for Azimuth (Seurat-based single-cell mapping) using rpy2
Home-page: https://github.com/KalinNonchev/azimuthpy
Author: Your Name
Author-email: your.email@example.com
License: MIT
Requires-Python: >=3.8
License-File: LICENSE
Requires-Dist: anndata
Requires-Dist: numpy
Requires-Dist: pandas
Requires-Dist: rpy2
